README.md
setup.py
gaiasdk/__init__.py
gaiasdk/job.py
gaiasdk/plugin_pb2.py
gaiasdk/plugin_pb2_grpc.py
gaiasdk/sdk.py
skarlsogaiasdk.egg-info/PKG-INFO
skarlsogaiasdk.egg-info/SOURCES.txt
skarlsogaiasdk.egg-info/dependency_links.txt
skarlsogaiasdk.egg-info/not-zip-safe
skarlsogaiasdk.egg-info/requires.txt
skarlsogaiasdk.egg-info/top_level.txt