Metadata-Version: 1.0
Name: skarlsogaiasdk
Version: 0.0.18
Summary: Test Gaia Python SDK Python 3 for python pipelines
Home-page: https://github.com/gaia-pipeline/pythonsdk
Author: Gergely Brautigam
Author-email: skarlso777@gmail.com
License: Apache-2.0
Platform: UNKNOWN
